[
 {
  "table":"TEXTPOOLT",
  "data":
  [
   {
    "ID":"I",
    "KEY":"B01",
    "LANG":"2",
    "ENTRY":"Program:",
    "LENGTH":8
   },
   {
    "ID":"I",
    "KEY":"B01",
    "LANG":"3",
    "ENTRY":"Program:",
    "LENGTH":8
   },
   {
    "ID":"I",
    "KEY":"B01",
    "LANG":"4",
    "ENTRY":"Program:",
    "LENGTH":8
   },
   {
    "ID":"I",
    "KEY":"B01",
    "LANG":"B",
    "ENTRY":"Program:",
    "LENGTH":8
   },
   {
    "ID":"I",
    "KEY":"B01",
    "LANG":"C",
    "ENTRY":"Program:",
    "LENGTH":8
   },
   {
    "ID":"I",
    "KEY":"B01",
    "LANG":"E",
    "ENTRY":"Program:",
    "LENGTH":8
   },
   {
    "ID":"I",
    "KEY":"B01",
    "LANG":"G",
    "ENTRY":"Program:",
    "LENGTH":8
   },
   {
    "ID":"I",
    "KEY":"B01",
    "LANG":"H",
    "ENTRY":"Program:",
    "LENGTH":8
   },
   {
    "ID":"I",
    "KEY":"B01",
    "LANG":"L",
    "ENTRY":"Program:",
    "LENGTH":8
   },
   {
    "ID":"I",
    "KEY":"B01",
    "LANG":"Q",
    "ENTRY":"Program:",
    "LENGTH":8
   },
   {
    "ID":"I",
    "KEY":"B01",
    "LANG":"R",
    "ENTRY":"Program:",
    "LENGTH":8
   },
   {
    "ID":"I",
    "KEY":"B01",
    "LANG":"T",
    "ENTRY":"Program:",
    "LENGTH":8
   },
   {
    "ID":"I",
    "KEY":"B01",
    "LANG":"묩",
    "ENTRY":"Program:",
    "LENGTH":8
   },
   {
    "ID":"I",
    "KEY":"VAL",
    "LANG":"2",
    "ENTRY":" (Test)",
    "LENGTH":11
   },
   {
    "ID":"I",
    "KEY":"VAL",
    "LANG":"3",
    "ENTRY":" (Test)",
    "LENGTH":11
   },
   {
    "ID":"I",
    "KEY":"VAL",
    "LANG":"4",
    "ENTRY":" (Test)",
    "LENGTH":11
   },
   {
    "ID":"I",
    "KEY":"VAL",
    "LANG":"B",
    "ENTRY":" (Test)",
    "LENGTH":11
   },
   {
    "ID":"I",
    "KEY":"VAL",
    "LANG":"C",
    "ENTRY":" (Test)",
    "LENGTH":11
   },
   {
    "ID":"I",
    "KEY":"VAL",
    "LANG":"E",
    "ENTRY":" (Test)",
    "LENGTH":11
   },
   {
    "ID":"I",
    "KEY":"VAL",
    "LANG":"G",
    "ENTRY":" (Test)",
    "LENGTH":11
   },
   {
    "ID":"I",
    "KEY":"VAL",
    "LANG":"H",
    "ENTRY":" (Test)",
    "LENGTH":11
   },
   {
    "ID":"I",
    "KEY":"VAL",
    "LANG":"L",
    "ENTRY":" (Test)",
    "LENGTH":11
   },
   {
    "ID":"I",
    "KEY":"VAL",
    "LANG":"Q",
    "ENTRY":" (Test)",
    "LENGTH":11
   },
   {
    "ID":"I",
    "KEY":"VAL",
    "LANG":"R",
    "ENTRY":" (Test)",
    "LENGTH":11
   },
   {
    "ID":"I",
    "KEY":"VAL",
    "LANG":"T",
    "ENTRY":" (Test)",
    "LENGTH":11
   },
   {
    "ID":"I",
    "KEY":"VAL",
    "LANG":"묩",
    "ENTRY":" (Test)",
    "LENGTH":11
   }
  ]
 }
]