[
 {
  "table":"DD25L",
  "data":
  [
   {
    "VIEWNAME":"EZFAM_LOG",
    "AS4LOCAL":"L",
    "AS4VERS":0,
    "AGGTYPE":"E",
    "APPLCLASS":"",
    "AUTHCLASS":0,
    "READONLY":"",
    "ROOTTAB":"ZFAM_LOG",
    "AS4USER":"KANUGOG",
    "AS4DATE":"2021-09-14",
    "AS4TIME":"13:07:53",
    "VIEWCLASS":"",
    "ACTFLAG":"",
    "MASTERLANG":"",
    "CUSTOMAUTH":"",
    "VIEWGRANT":"",
    "GLOBALFLAG":"",
    "MANKEY":"",
    "DBREFNAME":"",
    "ALLDATAINCL":"",
    "WITH_PARAMETERS":"",
    "EXVIEW_INCLUDED":"",
    "EXPR_IS_USED":"",
    "KEYMAX_FEATURE":"",
    "KEYLEN_FEATURE":"",
    "TABLEN_FEATURE":"",
    "NONTRP_INCLUDED":"",
    "VIEWREF":"",
    "VIEWREF_ERR":"",
    "VIEWREF_POS_CHG":"",
    "TBFUNC_INCLUDED":"",
    "SESSION_VAR_EX":"",
    "COMPRFLAG":"",
    "USED_SESSION_VARS":"",
    "ABAP_LANGUAGE_VERSION":"",
    "SHLPEXI":"",
    "HDB_ONLY_ENTITY_INCLUDED":""
   }
  ]
 },
 {
  "table":"DD25T",
  "data":
  [
   {
    "DDLANGUAGE":"B",
    "VIEWNAME":"EZFAM_LOG",
    "AS4LOCAL":"N",
    "AS4VERS":0,
    "DDTEXT":"Lock Object for Table ZFAM_LOG"
   },
   {
    "DDLANGUAGE":"E",
    "VIEWNAME":"EZFAM_LOG",
    "AS4LOCAL":"N",
    "AS4VERS":0,
    "DDTEXT":"Lock Object for Table ZFAM_LOG"
   },
   {
    "DDLANGUAGE":"묩",
    "VIEWNAME":"EZFAM_LOG",
    "AS4LOCAL":"N",
    "AS4VERS":0,
    "DDTEXT":"Lock Object for Table ZFAM_LOG"
   }
  ]
 },
 {
  "table":"DD26S",
  "data":
  [
   {
    "VIEWNAME":"EZFAM_LOG",
    "AS4LOCAL":"N",
    "TABNAME":"ZFAM_LOG",
    "AS4VERS":0,
    "TABPOS":1,
    "FORTABNAME":"ZFAM_LOG",
    "FORFIELD":"",
    "FORDIR":""
   }
  ]
 },
 {
  "table":"DD27S",
  "data":
  [
   {
    "VIEWNAME":"EZFAM_LOG",
    "AS4LOCAL":"N",
    "OBJPOS":1,
    "AS4VERS":0,
    "VIEWFIELD":"MANDT",
    "TABNAME":"ZFAM_LOG",
    "FIELDNAME":"MANDT",
    "KEYFLAG":"X",
    "MCFIELDID":"",
    "EFORM":"",
    "ROLLNAME":"MANDT",
    "ENQMODE":"",
    "RDONLY":"",
    "ROLLCHANGE":"",
    "DBVIEWFIELD":"",
    "EXVDATATYPE":"",
    "EXVFLENGTH":0,
    "EXVDECIMALS":0,
    "SQL_PASSVALUE":""
   },
   {
    "VIEWNAME":"EZFAM_LOG",
    "AS4LOCAL":"N",
    "OBJPOS":2,
    "AS4VERS":0,
    "VIEWFIELD":"FEATURE_ID",
    "TABNAME":"ZFAM_LOG",
    "FIELDNAME":"FEATURE_ID",
    "KEYFLAG":"X",
    "MCFIELDID":"",
    "EFORM":"",
    "ROLLNAME":"ZFAM_FEATURE_ID",
    "ENQMODE":"",
    "RDONLY":"",
    "ROLLCHANGE":"",
    "DBVIEWFIELD":"",
    "EXVDATATYPE":"",
    "EXVFLENGTH":0,
    "EXVDECIMALS":0,
    "SQL_PASSVALUE":""
   },
   {
    "VIEWNAME":"EZFAM_LOG",
    "AS4LOCAL":"N",
    "OBJPOS":3,
    "AS4VERS":0,
    "VIEWFIELD":"PROGNAME",
    "TABNAME":"ZFAM_LOG",
    "FIELDNAME":"PROGNAME",
    "KEYFLAG":"X",
    "MCFIELDID":"",
    "EFORM":"",
    "ROLLNAME":"PROGNAME",
    "ENQMODE":"",
    "RDONLY":"",
    "ROLLCHANGE":"",
    "DBVIEWFIELD":"",
    "EXVDATATYPE":"",
    "EXVFLENGTH":0,
    "EXVDECIMALS":0,
    "SQL_PASSVALUE":""
   },
   {
    "VIEWNAME":"EZFAM_LOG",
    "AS4LOCAL":"N",
    "OBJPOS":4,
    "AS4VERS":0,
    "VIEWFIELD":"PROGNAME",
    "TABNAME":"ZFAM_LOG",
    "FIELDNAME":"*",
    "KEYFLAG":"",
    "MCFIELDID":"",
    "EFORM":"",
    "ROLLNAME":"PROGNAME",
    "ENQMODE":"E",
    "RDONLY":"",
    "ROLLCHANGE":"",
    "DBVIEWFIELD":"",
    "EXVDATATYPE":"",
    "EXVFLENGTH":0,
    "EXVDECIMALS":0,
    "SQL_PASSVALUE":""
   }
  ]
 },
 {
  "table":"TADIR",
  "data":
  [
   {
    "PGMID":"R3TR",
    "OBJECT":"ENQU",
    "OBJ_NAME":"EZFAM_LOG",
    "KORRNUM":"",
    "SRCSYSTEM":"...",
    "AUTHOR":"RAOV",
    "SRCDEP":"",
    "DEVCLASS":"ZUTF_CONF_FAM",
    "GENFLAG":"",
    "EDTFLAG":"",
    "CPROJECT":" S",
    "MASTERLANG":"E",
    "VERSID":"0.0",
    "PAKNOCHECK":"",
    "OBJSTABLTY":"",
    "COMPONENT":"",
    "CRELEASE":"",
    "DELFLAG":"",
    "TRANSLTTXT":"",
    "CREATED_ON":"2020-09-11",
    "CHECK_DATE":"2020-09-11",
    "CHECK_CFG":""
   }
  ]
 }
]